secploy/__init__.py
secploy/client.py
secploy/enums.py
secploy/events.py
secploy/log_capture.py
secploy/processor.py
secploy/schemas.py
secploy/utils.py
secploy/lib/__init__.py
secploy/lib/config.py
secploy/lib/secploy_logger.py
secploy-0.2.7.dist-info/licenses/LICENSE
secploy-0.2.7.dist-info/METADATA
secploy-0.2.7.dist-info/WHEEL
secploy-0.2.7.dist-info/entry_points.txt
secploy-0.2.7.dist-info/top_level.txt
secploy-0.2.7.dist-info/RECORD
