Metadata-Version: 2.4
Name: secploy
Version: 0.2.7
Summary: Event tracking and monitoring SDK for Python applications
Home-page: https://github.com/agastronics/secploy-python-sdk
Author: Agastronics
Author-email: support@agastronics.com
Classifier: Development Status :: 4 - Beta
Classifier: Intended Audience :: Developers
Classifier: License :: OSI Approved :: MIT License
Classifier: Programming Language :: Python :: 3
Classifier: Programming Language :: Python :: 3.8
Classifier: Programming Language :: Python :: 3.9
Classifier: Programming Language :: Python :: 3.10
Classifier: Programming Language :: Python :: 3.11
License-File: LICENSE
Requires-Dist: requests>=2.25.0
Requires-Dist: pyyaml>=5.1
Requires-Dist: pydantic>=2.0.0
Dynamic: author
Dynamic: author-email
Dynamic: classifier
Dynamic: description
Dynamic: description-content-type
Dynamic: home-page
Dynamic: license-file
Dynamic: requires-dist
Dynamic: summary
